cfgy/__init__.py
cfgy/_version.py
cfgy/demo.py
cfgy/general.py
cfgy/yaml.py
cfgy-0.1.2.dist-info/METADATA
cfgy-0.1.2.dist-info/WHEEL
cfgy-0.1.2.dist-info/top_level.txt
cfgy-0.1.2.dist-info/zip-safe
cfgy-0.1.2.dist-info/RECORD
