Metadata-Version: 2.1
Name: cfgy
Version: 0.1.2
Summary: UNKNOWN
Home-page: https://github.com/jpn--/cfgy
Author: Jeff Newman
Author-email: jeff@newman.me
License: BSD-3-Clause
Platform: UNKNOWN
Requires-Python: >=3.7
Requires-Dist: pyyaml
Requires-Dist: yamllint
